metallicious/__init__.py
metallicious/__main__.py
metallicious/antechamber_interface.py
metallicious/asserts.py
metallicious/charges.py
metallicious/copy_topology_params.py
metallicious/data.py
metallicious/extract_metal_site.py
metallicious/improper_torsion.py
metallicious/initial_site.py
metallicious/load_fingerprint.py
metallicious/log.py
metallicious/mapping.py
metallicious/mod_seminario.py
metallicious/parametrize_new_sites.py
metallicious/patcher.py
metallicious/prepare_initial_topology.py
metallicious/seminario.py
metallicious/utils.py
metallicious/examples/__init__.py
metallicious/examples/example1_quick_start/example1.py
metallicious/examples/example1_quick_start/ru_pd.pdb
metallicious/examples/example1_quick_start/ru_pd.top
metallicious/examples/example2_no_topology/example2.py
metallicious/examples/example2_no_topology/ru_pd.xyz
metallicious/examples/example3_only_linker_topology/example3.py
metallicious/examples/example3_only_linker_topology/linker.top
metallicious/examples/example3_only_linker_topology/ru_pd.xyz
metallicious/examples/example4_truncation_scheme/cage.pdb
metallicious/examples/example4_truncation_scheme/example4.py
metallicious/examples/example4_truncation_scheme/topol.top
metallicious/examples/example5_protein/example5.py
metallicious/examples/example5_protein/protein.gro
metallicious/examples/example5_protein/protein.top
metallicious/examples/example6_mof/Co_mof.pdb
metallicious/examples/example6_mof/example6.py
metallicious/library/.Pd1.top.swn
metallicious/library/Co_2_merz-opc_0.pdb
metallicious/library/Co_2_merz-opc_0.top
metallicious/library/Co_2_merz-opc_4.pdb
metallicious/library/Co_2_merz-opc_4.top
metallicious/library/Co_2_merz-opc_5.pdb
metallicious/library/Co_2_merz-opc_5.top
metallicious/library/Co_2_merz-opc_6.pdb
metallicious/library/Co_2_merz-opc_6.top
metallicious/library/Co_2_merz-opc_7.pdb
metallicious/library/Co_2_merz-opc_7.top
metallicious/library/Co_2_merz-opc_8.pdb
metallicious/library/Co_2_merz-opc_8.top
metallicious-0.2.34.dist-info/LICENSE.md
metallicious-0.2.34.dist-info/METADATA
metallicious-0.2.34.dist-info/WHEEL
metallicious-0.2.34.dist-info/entry_points.txt
metallicious-0.2.34.dist-info/top_level.txt
metallicious-0.2.34.dist-info/RECORD
