Metadata-Version: 2.1
Name: metallicious
Version: 0.2.34
License-File: LICENSE.md
Requires-Dist: numpy
Requires-Dist: MDAnalysis
Requires-Dist: rdkit
Requires-Dist: parmed
Requires-Dist: networkx
